[
  {
    "address": "United Kingdom",
    "amount": 500,
    "connections": 1,
    "email": "",
    "global_index": 25,
    "is_ghost_image": true,
    "last_donation_date": "2024-12-12T12:51:52.000Z",
    "last_donation_time_ago": "1 day ago",
    "name": "Deirdre Mackel",
    "url": "https://www.linkedin.com/in/deirdre-mackel-93114638"
  },
  {
    "address": "Toronto, Ontario, Canada",
    "amount": 367,
    "connections": 0,
    "email": "",
    "global_index": 271,
    "is_ghost_image": true,
    "last_donation_date": "2024-12-12T01:05:58.000Z",
    "last_donation_time_ago": "1 day ago",
    "name": "Stephan Goslinski",
    "url": "https://www.linkedin.com/in/stephan-goslinski-1909a2277"
  },
  {
    "address": "Greater Rockford Area",
    "amount": 200,
    "connections": 43,
    "email": "",
    "global_index": 497,
    "is_ghost_image": false,
    "last_donation_date": "2024-12-12T01:11:33.000Z",
    "last_donation_time_ago": "1 day ago",
    "name": "Kathryn Shihadah",
    "url": "https://www.linkedin.com/in/kathryn-shihadah-84021519a"
  },
  {
    "address": "Yonkers, New York, United States",
    "amount": 150,
    "connections": 2,
    "email": "",
    "global_index": 39,
    "is_ghost_image": true,
    "last_donation_date": "2024-12-12T02:16:28.000Z",
    "last_donation_time_ago": "1 day ago",
    "name": "vivienne murrihy",
    "url": "https://www.linkedin.com/in/vivienne-murrihy-a01b1b6"
  },
  {
    "address": "United Kingdom",
    "amount": 100,
    "connections": 1,
    "email": "",
    "global_index": 69,
    "is_ghost_image": true,
    "last_donation_date": "2024-12-12T19:59:58.000Z",
    "last_donation_time_ago": "1 day ago",
    "name": "clive gash",
    "url": "https://www.linkedin.com/in/clive-gash-44716442"
  },
  {
    "address": "Ireland",
    "amount": 100,
    "connections": 500,
    "email": "",
    "global_index": 84,
    "is_ghost_image": false,
    "last_donation_date": "2024-12-12T13:37:46.000Z",
    "last_donation_time_ago": "1 day ago",
    "name": "Julian de Spáinn",
    "url": "https://www.linkedin.com/in/julian-de-sp%C3%A1inn-817a8719"
  },
  {
    "address": "Singapore",
    "amount": 100,
    "connections": 79,
    "email": "",
    "global_index": 284,
    "is_ghost_image": true,
    "last_donation_date": "2024-12-13T01:45:55.000Z",
    "last_donation_time_ago": "20 hours ago",
    "name": "Aysha reema Muhusin",
    "url": "https://www.linkedin.com/in/aysha-reema-muhusin-41170b56"
  },
  {
    "address": "Algeria",
    "amount": 100,
    "connections": 0,
    "email": "",
    "global_index": 286,
    "is_ghost_image": true,
    "last_donation_date": "2024-12-12T22:19:10.000Z",
    "last_donation_time_ago": "23 hours ago",
    "name": "Imad Pidro",
    "url": "https://www.linkedin.com/in/imad-pidro-19a605158"
  },
  {
    "address": "Greater Phoenix Area",
    "amount": 100,
    "connections": 121,
    "email": "",
    "global_index": 294,
    "is_ghost_image": false,
    "last_donation_date": "2024-12-12T01:20:18.000Z",
    "last_donation_time_ago": "1 day ago",
    "name": "Juhaynah Lewis",
    "url": "https://www.linkedin.com/in/juhaynahlewis"
  },
  {
    "address": "New York, New York, United States",
    "amount": 100,
    "connections": 500,
    "email": "",
    "global_index": 298,
    "is_ghost_image": true,
    "last_donation_date": "2024-12-11T22:52:19.000Z",
    "last_donation_time_ago": "1 day ago",
    "name": "Anikah Shaokat",
    "url": "https://www.linkedin.com/in/anikah-shaokat-79aa9687"
  },
  {
    "address": "Greater Seattle Area",
    "amount": 100,
    "connections": 500,
    "email": "",
    "global_index": 420,
    "is_ghost_image": true,
    "last_donation_date": "2024-12-12T14:59:41.000Z",
    "last_donation_time_ago": "1 day ago",
    "name": "Deena Claudio",
    "url": "https://www.linkedin.com/in/deena-claudio-5a418a15"
  },
  {
    "address": "Gambier, Ohio, United States",
    "amount": 50,
    "connections": 254,
    "email": "",
    "global_index": 5,
    "is_ghost_image": false,
    "last_donation_date": "2024-12-12T14:42:36.000Z",
    "last_donation_time_ago": "1 day ago",
    "name": "Eve Kausch",
    "url": "https://www.linkedin.com/in/eve-kausch-308592164"
  },
  {
    "address": "Qatar",
    "amount": 50,
    "connections": 11,
    "email": "",
    "global_index": 133,
    "is_ghost_image": true,
    "last_donation_date": "2024-12-13T00:30:05.000Z",
    "last_donation_time_ago": "21 hours ago",
    "name": "Aileen McShane",
    "url": "https://www.linkedin.com/in/aileen-mcshane-2730ab63"
  },
  {
    "address": "Greater Cheshire West and Chester Area",
    "amount": 50,
    "connections": 2,
    "email": "",
    "global_index": 148,
    "is_ghost_image": true,
    "last_donation_date": "2024-12-12T22:03:35.000Z",
    "last_donation_time_ago": "1 day ago",
    "name": "Gillian Mounsey",
    "url": "https://www.linkedin.com/in/gillian-mounsey-abaab719a"
  },
  {
    "address": "Ireland",
    "amount": 50,
    "connections": 1,
    "email": "",
    "global_index": 152,
    "is_ghost_image": true,
    "last_donation_date": "2024-12-12T21:33:27.000Z",
    "last_donation_time_ago": "1 day ago",
    "name": "Raymonte Desmond",
    "url": "https://www.linkedin.com/in/raymonte-desmond-a1392399"
  },
  {
    "address": "Enniskillen, Northern Ireland, United Kingdom",
    "amount": 50,
    "connections": 3,
    "email": "",
    "global_index": 235,
    "is_ghost_image": true,
    "last_donation_date": "2024-12-12T09:33:53.000Z",
    "last_donation_time_ago": "1 day ago",
    "name": "Aoibhinn McGoldrick",
    "url": "https://www.linkedin.com/in/aoibhinn-mcgoldrick-39a359249"
  },
  {
    "address": "London, England, United Kingdom",
    "amount": 50,
    "connections": 500,
    "email": "",
    "global_index": 303,
    "is_ghost_image": false,
    "last_donation_date": "2024-12-13T08:23:32.000Z",
    "last_donation_time_ago": "13 hours ago",
    "name": "Helene Theros",
    "url": "https://www.linkedin.com/in/helene-theros-28641b14"
  },
  {
    "address": "Oklahoma City Metropolitan Area",
    "amount": 50,
    "connections": 5,
    "email": "",
    "global_index": 307,
    "is_ghost_image": false,
    "last_donation_date": "2024-12-12T20:13:42.000Z",
    "last_donation_time_ago": "1 day ago",
    "name": "Nicole Kammerlocher",
    "url": "https://www.linkedin.com/in/nicole-kammerlocher-423333191"
  },
  {
    "address": "New York, New York, United States",
    "amount": 50,
    "connections": 0,
    "email": "",
    "global_index": 310,
    "is_ghost_image": false,
    "last_donation_date": "2024-12-12T16:05:16.000Z",
    "last_donation_time_ago": "1 day ago",
    "name": "Sarah Lotvin",
    "url": "https://www.linkedin.com/in/sarah-lotvin-b65965321"
  },
  {
    "address": "United States",
    "amount": 50,
    "connections": 201,
    "email": "",
    "global_index": 318,
    "is_ghost_image": false,
    "last_donation_date": "2024-12-12T22:43:10.000Z",
    "last_donation_time_ago": "23 hours ago",
    "name": "Kayla Ramjohn",
    "url": "https://www.linkedin.com/in/kayla-ramjohn-513830191"
  },
  {
    "address": "Calamvale, Queensland, Australia",
    "amount": 50,
    "connections": 0,
    "email": "",
    "global_index": 333,
    "is_ghost_image": false,
    "last_donation_date": "2024-12-12T22:34:32.000Z",
    "last_donation_time_ago": "23 hours ago",
    "name": "Carly Jostsons",
    "url": "https://www.linkedin.com/in/carly-jostsons-a5207830a"
  },
  {
    "address": "Greater Reading Area",
    "amount": 50,
    "connections": 2,
    "email": "",
    "global_index": 340,
    "is_ghost_image": true,
    "last_donation_date": "2024-12-13T19:32:31.000Z",
    "last_donation_time_ago": "2 hours ago",
    "name": "Krystelle Kamola",
    "url": "https://www.linkedin.com/in/krystelle-kamola-a4121788"
  },
  {
    "address": "London, England, United Kingdom",
    "amount": 50,
    "connections": 51,
    "email": "",
    "global_index": 341,
    "is_ghost_image": true,
    "last_donation_date": "2024-12-13T19:13:56.000Z",
    "last_donation_time_ago": "3 hours ago",
    "name": "Sukey Firth",
    "url": "https://www.linkedin.com/in/sukey-firth-7ba3a511"
  },
  {
    "address": "United States",
    "amount": 50,
    "connections": 130,
    "email": "",
    "global_index": 363,
    "is_ghost_image": true,
    "last_donation_date": "2024-12-13T06:07:29.000Z",
    "last_donation_time_ago": "16 hours ago",
    "name": "Zuhal Qaderdan",
    "url": "https://www.linkedin.com/in/zuhal-qaderdan-a39402208"
  },
  {
    "address": "New York City Metropolitan Area",
    "amount": 50,
    "connections": 2,
    "email": "",
    "global_index": 398,
    "is_ghost_image": true,
    "last_donation_date": "2024-12-11T23:35:27.000Z",
    "last_donation_time_ago": "1 day ago",
    "name": "Marshall Wegh",
    "url": "https://www.linkedin.com/in/marshall-wegh-45522abb"
  },
  {
    "address": "Sterling, Virginia, United States",
    "amount": 50,
    "connections": 253,
    "email": "",
    "global_index": 399,
    "is_ghost_image": false,
    "last_donation_date": "2024-12-13T14:57:47.000Z",
    "last_donation_time_ago": "7 hours ago",
    "name": "Steffi Walthall",
    "url": "https://www.linkedin.com/in/steffi-walthall"
  },
  {
    "address": "United Arab Emirates",
    "amount": 50,
    "connections": 500,
    "email": "",
    "global_index": 424,
    "is_ghost_image": false,
    "last_donation_date": "2024-12-13T16:35:22.000Z",
    "last_donation_time_ago": "5 hours ago",
    "name": "Mai Abdeljaber",
    "url": "https://www.linkedin.com/in/mai-abdeljaber-abb432a"
  },
  {
    "address": "United States",
    "amount": 50,
    "connections": 1,
    "email": "",
    "global_index": 427,
    "is_ghost_image": true,
    "last_donation_date": "2024-12-13T00:52:01.000Z",
    "last_donation_time_ago": "21 hours ago",
    "name": "Joan Cocanour",
    "url": "https://www.linkedin.com/in/joan-cocanour-808968a0"
  },
  {
    "address": "Dubai, United Arab Emirates",
    "amount": 50,
    "connections": 500,
    "email": "",
    "global_index": 461,
    "is_ghost_image": false,
    "last_donation_date": "2024-12-13T02:36:30.000Z",
    "last_donation_time_ago": "19 hours ago",
    "name": "Dania Zegallai",
    "url": "https://www.linkedin.com/in/dania-zegallai"
  },
  {
    "address": "Arlington, Texas, United States",
    "amount": 50,
    "connections": 80,
    "email": "",
    "global_index": 468,
    "is_ghost_image": false,
    "last_donation_date": "2024-12-13T03:00:52.000Z",
    "last_donation_time_ago": "19 hours ago",
    "name": "Aasiyah Akbari",
    "url": "https://www.linkedin.com/in/aasiyah-akbari-5904b1174"
  },
  {
    "address": "Taverny, Île-de-France, France",
    "amount": 50,
    "connections": 249,
    "email": "",
    "global_index": 487,
    "is_ghost_image": false,
    "last_donation_date": "2024-12-12T21:00:23.000Z",
    "last_donation_time_ago": "1 day ago",
    "name": "DJAMIN Medjahed",
    "url": "https://www.linkedin.com/in/djamin-medjahed-b91380222"
  },
  {
    "address": "Camp Hill, Pennsylvania, United States",
    "amount": 50,
    "connections": 193,
    "email": "",
    "global_index": 492,
    "is_ghost_image": true,
    "last_donation_date": "2024-12-13T12:22:46.000Z",
    "last_donation_time_ago": "10 hours ago",
    "name": "Felecia Khorram",
    "url": "https://www.linkedin.com/in/felecia-khorram-b28732ab"
  },
  {
    "address": "United States",
    "amount": 50,
    "connections": 8,
    "email": "",
    "global_index": 493,
    "is_ghost_image": true,
    "last_donation_date": "2024-12-12T20:32:00.000Z",
    "last_donation_time_ago": "1 day ago",
    "name": "Rima Bensrieti",
    "url": "https://www.linkedin.com/in/rima-bensrieti-27559a28"
  },
  {
    "address": "Alameda, California, United States",
    "amount": 50,
    "connections": 58,
    "email": "",
    "global_index": 494,
    "is_ghost_image": false,
    "last_donation_date": "2024-12-13T15:30:52.000Z",
    "last_donation_time_ago": "6 hours ago",
    "name": "Tairen Parker",
    "url": "https://www.linkedin.com/in/tairen-parker-44b224233"
  },
  {
    "address": "Portland, Oregon, United States",
    "amount": 50,
    "connections": 123,
    "email": "",
    "global_index": 499,
    "is_ghost_image": false,
    "last_donation_date": "2024-12-12T00:56:21.000Z",
    "last_donation_time_ago": "1 day ago",
    "name": "Devon Paldi",
    "url": "https://www.linkedin.com/in/devon-paldi-40919614"
  },
  {
    "address": "Marseille, Provence-Alpes-Côte d'Azur, France",
    "amount": 50,
    "connections": 500,
    "email": "",
    "global_index": 525,
    "is_ghost_image": false,
    "last_donation_date": "2024-12-13T17:01:16.000Z",
    "last_donation_time_ago": "5 hours ago",
    "name": "Sami MHIDIA",
    "url": "https://www.linkedin.com/in/sami-mhidia"
  },
  {
    "address": "United States",
    "amount": 50,
    "connections": 0,
    "email": "",
    "global_index": 535,
    "is_ghost_image": true,
    "last_donation_date": "2024-12-12T18:10:58.000Z",
    "last_donation_time_ago": "1 day ago",
    "name": "Tayir Pugh",
    "url": "https://www.linkedin.com/in/tayir-pugh-745897174"
  },
  {
    "address": "Seattle, Washington, United States",
    "amount": 50,
    "connections": 93,
    "email": "",
    "global_index": 539,
    "is_ghost_image": true,
    "last_donation_date": "2024-12-13T06:06:50.000Z",
    "last_donation_time_ago": "16 hours ago",
    "name": "Etsuko Garcia",
    "url": "https://www.linkedin.com/in/etsuko-garcia-b93252122"
  },
  {
    "address": "Minneapolis, Minnesota, United States",
    "amount": 100,
    "connections": 289,
    "email": "",
    "global_index": 547,
    "is_ghost_image": false,
    "last_donation_date": "2024-12-12T02:50:07.000Z",
    "last_donation_time_ago": "1 day ago",
    "name": "Puja Mahinkanda",
    "url": "https://www.linkedin.com/in/puja-mahinkanda-b884a61a"
  },
  {
    "address": "Iceland",
    "amount": 200,
    "connections": 500,
    "email": "",
    "global_index": 553,
    "is_ghost_image": true,
    "last_donation_date": "2024-12-13T15:18:34.000Z",
    "last_donation_time_ago": "7 hours ago",
    "name": "Elisabet Ronaldsdottir",
    "url": "https://www.linkedin.com/in/elisabetronalds"
  },
  {
    "address": "United Arab Emirates",
    "amount": 100,
    "connections": 500,
    "email": "",
    "global_index": 556,
    "is_ghost_image": false,
    "last_donation_date": "2024-12-12T22:21:27.000Z",
    "last_donation_time_ago": "1 day ago",
    "name": "alaa mehram",
    "url": "https://www.linkedin.com/in/alaa-mehram-resume"
  },
  {
    "address": "Greater Paris Metropolitan Region",
    "amount": 150,
    "connections": 419,
    "email": "",
    "global_index": 561,
    "is_ghost_image": true,
    "last_donation_date": "2024-12-12T22:04:37.000Z",
    "last_donation_time_ago": "1 day ago",
    "name": "Marwan Halloumi",
    "url": "https://www.linkedin.com/in/marwan-halloumi-b8b56634"
  },
  {
    "address": "London, England, United Kingdom",
    "amount": 50,
    "connections": 36,
    "email": "",
    "global_index": 563,
    "is_ghost_image": false,
    "last_donation_date": "2024-12-12T21:41:53.000Z",
    "last_donation_time_ago": "1 day ago",
    "name": "Khatera Amirzadah",
    "url": "https://www.linkedin.com/in/khatera-amirzadah-37b227155"
  },
  {
    "address": "Albany, New York, United States",
    "amount": 50,
    "connections": 374,
    "email": "",
    "global_index": 564,
    "is_ghost_image": false,
    "last_donation_date": "2024-12-13T20:55:32.000Z",
    "last_donation_time_ago": "1 hour ago",
    "name": "Rebecca Colesworthy",
    "url": "https://www.linkedin.com/in/rebeccacolesworthy"
  },
  {
    "address": "Frisco, Texas, United States",
    "amount": 100,
    "connections": 500,
    "email": "",
    "global_index": 565,
    "is_ghost_image": true,
    "last_donation_date": "2024-12-13T18:17:25.000Z",
    "last_donation_time_ago": "4 hours ago",
    "name": "Ankita Bantey",
    "url": "https://www.linkedin.com/in/ankita-bantey"
  },
  {
    "address": "Ventura, California, United States",
    "amount": 50,
    "connections": 1,
    "email": "",
    "global_index": 581,
    "is_ghost_image": false,
    "last_donation_date": "2024-12-12T05:09:02.000Z",
    "last_donation_time_ago": "1 day ago",
    "name": "Kyan Ramirez",
    "url": "https://www.linkedin.com/in/kyan-ramirez-1377432a3"
  },
  {
    "address": "Iceland",
    "amount": 50,
    "connections": 29,
    "email": "",
    "global_index": 584,
    "is_ghost_image": false,
    "last_donation_date": "2024-12-12T00:11:38.000Z",
    "last_donation_time_ago": "1 day ago",
    "name": "Anna Margrét Sigurbergsdóttir",
    "url": "https://www.linkedin.com/in/anna-margret-sig"
  },
  {
    "address": "Madison, Wisconsin, United States",
    "amount": 50,
    "connections": 44,
    "email": "",
    "global_index": 596,
    "is_ghost_image": false,
    "last_donation_date": "2024-12-12T15:58:40.000Z",
    "last_donation_time_ago": "1 day ago",
    "name": "Leanny Barrios",
    "url": "https://www.linkedin.com/in/leannybarrios"
  },
  {
    "address": "Southsea, England, United Kingdom",
    "amount": 50,
    "connections": 0,
    "email": "",
    "global_index": 600,
    "is_ghost_image": true,
    "last_donation_date": "2024-12-12T20:17:56.000Z",
    "last_donation_time_ago": "1 day ago",
    "name": "Alfie Kimber",
    "url": "https://www.linkedin.com/in/alfie-kimber-8515aa1b9"
  },
  {
    "address": "Copertino, Apulia, Italy",
    "amount": 50,
    "connections": 429,
    "email": "",
    "global_index": 603,
    "is_ghost_image": false,
    "last_donation_date": "2024-12-12T15:41:39.000Z",
    "last_donation_time_ago": "1 day ago",
    "name": "Ademaura Suriano",
    "url": "https://www.linkedin.com/in/ademaura-suriano-187a4b139"
  },
  {
    "address": "Halle, Saxony-Anhalt, Germany",
    "amount": 50,
    "connections": 2,
    "email": "",
    "global_index": 611,
    "is_ghost_image": false,
    "last_donation_date": "2024-12-12T17:31:48.000Z",
    "last_donation_time_ago": "1 day ago",
    "name": "Paul Henßge",
    "url": "https://www.linkedin.com/in/paul-hen%C3%9Fge-1b7585246"
  },
  {
    "address": "London Area, United Kingdom",
    "amount": 50,
    "connections": 500,
    "email": "",
    "global_index": 636,
    "is_ghost_image": false,
    "last_donation_date": "2024-12-12T21:28:06.000Z",
    "last_donation_time_ago": "1 day ago",
    "name": "Michaela Boitin",
    "url": "https://www.linkedin.com/in/michaelaboitin"
  },
  {
    "address": "Orlando, Florida, United States",
    "amount": 50,
    "connections": 284,
    "email": "",
    "global_index": 643,
    "is_ghost_image": false,
    "last_donation_date": "2024-12-13T21:32:02.000Z",
    "last_donation_time_ago": "1 hour ago",
    "name": "Takmila Choudhury",
    "url": "https://www.linkedin.com/in/takmila"
  },
  {
    "address": "Greater Portsmouth Area",
    "amount": 100,
    "connections": 8,
    "email": "",
    "global_index": 657,
    "is_ghost_image": true,
    "last_donation_date": "2024-12-13T17:30:38.000Z",
    "last_donation_time_ago": "5 hours ago",
    "name": "Hawwa Bobat",
    "url": "https://www.linkedin.com/in/hawwa-bobat-4b203361"
  },
  {
    "address": "New York, New York, United States",
    "amount": 50,
    "connections": 91,
    "email": "",
    "global_index": 680,
    "is_ghost_image": true,
    "last_donation_date": "2024-12-12T13:01:59.000Z",
    "last_donation_time_ago": "1 day ago",
    "name": "Amy Bilancini",
    "url": "https://www.linkedin.com/in/amy-bilancini-52571612"
  },
  {
    "address": "Eidsvoll, Viken, Norway",
    "amount": 421,
    "connections": 2,
    "email": "",
    "global_index": 681,
    "is_ghost_image": true,
    "last_donation_date": "2024-12-13T15:09:50.000Z",
    "last_donation_time_ago": "7 hours ago",
    "name": "Ismat Wahdan",
    "url": "https://www.linkedin.com/in/ismat-wahdan-422378238"
  },
  {
    "address": "Urbandale, Iowa, United States",
    "amount": 100,
    "connections": 500,
    "email": "",
    "global_index": 688,
    "is_ghost_image": false,
    "last_donation_date": "2024-12-13T21:25:16.000Z",
    "last_donation_time_ago": "1 hour ago",
    "name": "Marion Ajiri",
    "url": "https://www.linkedin.com/in/marionknight"
  },
  {
    "address": "United States",
    "amount": 50,
    "connections": 1,
    "email": "",
    "global_index": 694,
    "is_ghost_image": false,
    "last_donation_date": "2024-12-12T08:46:03.000Z",
    "last_donation_time_ago": "1 day ago",
    "name": "Cholifah Clough",
    "url": "https://www.linkedin.com/in/cholifah-clough-51042160"
  },
  {
    "address": "Carmichael, California, United States",
    "amount": 120,
    "connections": 16,
    "email": "",
    "global_index": 707,
    "is_ghost_image": true,
    "last_donation_date": "2024-12-12T19:41:18.000Z",
    "last_donation_time_ago": "1 day ago",
    "name": "Esther Gayoba",
    "url": "https://www.linkedin.com/in/esther-gayoba-946b5511b"
  }
]